schorg/AMRadioChannel.py
schorg/APIReference.py
schorg/Abdomen.py
schorg/AboutPage.py
schorg/AcceptAction.py
schorg/Accommodation.py
schorg/AccountingService.py
schorg/AchieveAction.py
schorg/Action.py
schorg/ActionAccessSpecification.py
schorg/ActionStatusType.py
schorg/ActivateAction.py
schorg/ActivationFee.py
schorg/ActiveActionStatus.py
schorg/ActiveNotRecruiting.py
schorg/AddAction.py
schorg/AdministrativeArea.py
schorg/AdultEntertainment.py
schorg/AdultOrientedEnumeration.py
schorg/AdvertiserContentArticle.py
schorg/AerobicActivity.py
schorg/AggregateOffer.py
schorg/AggregateRating.py
schorg/AgreeAction.py
schorg/Airline.py
schorg/Airport.py
schorg/AlbumRelease.py
schorg/AlcoholConsideration.py
schorg/AlignmentObject.py
schorg/AllWheelDriveConfiguration.py
schorg/AllergiesHealthAspect.py
schorg/AllocateAction.py
schorg/AmpStory.py
schorg/AmusementPark.py
schorg/AnaerobicActivity.py
schorg/AnalysisNewsArticle.py
schorg/AnatomicalStructure.py
schorg/AnatomicalSystem.py
schorg/AndroidPlatform.py
schorg/Anesthesia.py
schorg/AnimalShelter.py
schorg/Answer.py
schorg/Apartment.py
schorg/ApartmentComplex.py
schorg/Appearance.py
schorg/AppendAction.py
schorg/ApplyAction.py
schorg/ApprovedIndication.py
schorg/Aquarium.py
schorg/ArchiveComponent.py
schorg/ArchiveOrganization.py
schorg/ArriveAction.py
schorg/ArtGallery.py
schorg/Artery.py
schorg/Article.py
schorg/AskAction.py
schorg/AskPublicNewsArticle.py
schorg/AssessAction.py
schorg/AssignAction.py
schorg/Atlas.py
schorg/Attorney.py
schorg/Audience.py
schorg/AudioObject.py
schorg/AudioObjectSnapshot.py
schorg/Audiobook.py
schorg/AudiobookFormat.py
schorg/AuthoritativeLegalValue.py
schorg/AuthorizeAction.py
schorg/AutoBodyShop.py
schorg/AutoDealer.py
schorg/AutoPartsStore.py
schorg/AutoRental.py
schorg/AutoRepair.py
schorg/AutoWash.py
schorg/AutomatedTeller.py
schorg/AutomotiveBusiness.py
schorg/Ayurvedic.py
schorg/BackOrder.py
schorg/BackgroundNewsArticle.py
schorg/Bacteria.py
schorg/Bakery.py
schorg/Balance.py
schorg-0.7.5.dist-info/LICENSE
schorg-0.7.5.dist-info/WHEEL
schorg-0.7.5.dist-info/METADATA
schorg-0.7.5.dist-info/RECORD
