Metadata-Version: 2.1
Name: schorg
Version: 0.7.5
Summary: Pydantic classes for Schema.org.
Home-page: https://github.com/aulring/schorg
License: MIT
Keywords: schema.org,pydantic,schemaorg
Author: Adam Ulring
Author-email: adam.ulring1@gmail.com
Classifier: License :: OSI Approved :: MIT License
Classifier: Programming Language :: Python :: 2
Classifier: Programming Language :: Python :: 2.7
Classifier: Programming Language :: Python :: 3
Classifier: Programming Language :: Python :: 3.10
Classifier: Programming Language :: Python :: 3.4
Classifier: Programming Language :: Python :: 3.5
Classifier: Programming Language :: Python :: 3.6
Classifier: Programming Language :: Python :: 3.7
Classifier: Programming Language :: Python :: 3.8
Classifier: Programming Language :: Python :: 3.9
Requires-Dist: pydantic (>=1.8.2,<2.0.0)
Project-URL: Documentation, https://storage.googleapis.com/schorg-docs/index.html
Project-URL: Repository, https://github.com/aulring/schorg
